pyelling/__init__.py
pyelling/cipher.py
pyelling/emotional_styles.py
pyelling/internet_effects.py
pyelling/sound_effects.py
pyelling/text_volume.py
pyelling-0.1.0.dist-info/licenses/LICENSE
tests/__init__.py
tests/test_cipher.py
tests/test_emotional_styles.py
tests/test_internet_effects.py
tests/test_sound_effects.py
tests/test_text_volume.py
pyelling-0.1.0.dist-info/METADATA
pyelling-0.1.0.dist-info/WHEEL
pyelling-0.1.0.dist-info/top_level.txt
pyelling-0.1.0.dist-info/RECORD
