Metadata-Version: 2.4
Name: pyelling
Version: 0.1.0
Summary: A Python package for text TRANSFORMATION!
Home-page: https://github.com/samcofer/pyell
Author: Python Port of YELLING by Hadley Wickham
Author-email: Python Port of YELLING by Hadley Wickham <example@example.com>
License: MIT
Project-URL: Homepage, https://github.com/samcofer/pyell
Project-URL: Bug Tracker, https://github.com/samcofer/pyell/issues
Keywords: text,transformation,fun,formatting
Classifier: Programming Language :: Python :: 3
Classifier: License :: OSI Approved :: MIT License
Classifier: Operating System :: OS Independent
Classifier: Development Status :: 4 - Beta
Classifier: Intended Audience :: Developers
Classifier: Topic :: Text Processing
Requires-Python: >=3.6
License-File: LICENSE
Dynamic: author
Dynamic: home-page
Dynamic: license-file
Dynamic: requires-python
